// class version 61.0 (61)
// access flags 0x1
public class Main {


  // access flags 0x1
  public <init>()V
    ALOAD 0
    INVOKESPECIAL java/lang/Object.<init> ()V
    RETURN
    MAXSTACK = 1
    MAXLOCALS = 1

  // access flags 0x9
  public static main([Ljava/lang/String;)V
    NEW A
    DUP
    INVOKESPECIAL A.<init> ()V
    ASTORE 0
    NEW A
    DUP
    INVOKESPECIAL A.<init> ()V
    ASTORE 1
    ALOAD 1
    ALOAD 0
    ALOAD 1
    PUTFIELD A.other : LA;
    ALOAD 0
    ALOAD 1
    ALOAD 0
    PUTFIELD A.other : LA;
    ALOAD 0
    DUP
    IFNONNULL L0
    NEW java/lang/NullPointerException
    DUP
    INVOKESPECIAL java/lang/NullPointerException.<init> ()V
    ATHROW
   L0
    GETFIELD A.other : LA;
    ALOAD 1
    IF_ACMPNE L1
    GETSTATIC java/lang/System.out : Ljava/io/PrintStream;
    LDC "ok"
    INVOKEVIRTUAL java/io/PrintStream.print (Ljava/lang/String;)V
    GOTO L2
   L1
   L2
    ALOAD 1
    DUP
    IFNONNULL L3
    NEW java/lang/NullPointerException
    DUP
    INVOKESPECIAL java/lang/NullPointerException.<init> ()V
    ATHROW
   L3
    GETFIELD A.other : LA;
    ALOAD 0
    IF_ACMPNE L4
    GETSTATIC java/lang/System.out : Ljava/io/PrintStream;
    LDC "ok"
    INVOKEVIRTUAL java/io/PrintStream.print (Ljava/lang/String;)V
    GOTO L5
   L4
   L5
    RETURN
    MAXSTACK = 0
    MAXLOCALS = 0
}
